hypha/VERSION
hypha/__init__.py
hypha/__main__.py
hypha/a2a.py
hypha/admin.py
hypha/apps.py
hypha/artifact.py
hypha/http.py
hypha/http_rpc.py
hypha/interactive.py
hypha/local_auth.py
hypha/mcp.py
hypha/minio.py
hypha/pgvector.py
hypha/plugin_parser.py
hypha/queue.py
hypha/s3.py
hypha/s3vector.py
hypha/server.py
hypha/startup.py
hypha/triton.py
hypha/vectors.py
hypha/websocket.py
hypha/core/__init__.py
hypha/core/activity.py
hypha/core/auth.py
hypha/core/store.py
hypha/core/workspace.py
hypha/git/__init__.py
hypha/git/artifact_integration.py
hypha/git/http.py
hypha/git/lfs.py
hypha/git/object_store.py
hypha/git/refs.py
hypha/git/repo.py
hypha/git/s3_async.py
hypha/static_files/hypha-rpc-version.txt
hypha/static_files/hypha-rpc-websocket.js
hypha/static_files/hypha-rpc-websocket.mjs
hypha/static_files/lite.html
hypha/static_files/img/hypha-icon-black.svg
hypha/static_files/img/hypha-logo-black.svg
hypha/templates/index.html
hypha/templates/apps/imjoy-plugin-parser.html
hypha/templates/apps/login_template.html
hypha/templates/apps/web-python.index.html
hypha/templates/apps/web-worker.index.html
hypha/templates/apps/window.index.html
hypha/templates/artifacts/application/index.html
hypha/templates/artifacts/collection/index.html
hypha/templates/hypha-core-app/hypha-app-iframe.html
hypha/templates/hypha-core-app/hypha-app-webpython.js
hypha/templates/hypha-core-app/hypha-app-webworker.js
hypha/templates/ws/a2a_agent_template.hypha.html
hypha/templates/ws/code_template.hypha.html
hypha/templates/ws/conda_jupyter_kernel_template.hypha.html
hypha/templates/ws/fastapi_advanced_template.hypha.html
hypha/templates/ws/fastapi_app_template.hypha.html
hypha/templates/ws/index.html
hypha/templates/ws/javascript_advanced_template.hypha.html
hypha/templates/ws/javascript_app_template.hypha.html
hypha/templates/ws/mcp_server_template.hypha.html
hypha/templates/ws/python_app_template.hypha.html
hypha/templates/ws/web_app_template.hypha.html
hypha-0.21.39.dist-info/LICENSE
hypha-0.21.39.dist-info/METADATA
hypha-0.21.39.dist-info/WHEEL
hypha-0.21.39.dist-info/entry_points.txt
hypha-0.21.39.dist-info/top_level.txt
hypha-0.21.39.dist-info/RECORD
